TISControlProtocol/BytesHelper.py
TISControlProtocol/__init__.py
TISControlProtocol/api.py
TISControlProtocol/crc.py
TISControlProtocol/logo.png
TISControlProtocol/package-lock.json
TISControlProtocol/package.json
TISControlProtocol/postcss.config.mjs
TISControlProtocol/shared.py
TISControlProtocol/Protocols/__init__.py
TISControlProtocol/Protocols/udp/AckCoordinator.py
TISControlProtocol/Protocols/udp/PacketDispatcher.py
TISControlProtocol/Protocols/udp/PacketExtractor.py
TISControlProtocol/Protocols/udp/PacketProtocol.py
TISControlProtocol/Protocols/udp/PacketReceiver.py
TISControlProtocol/Protocols/udp/PacketSender.py
TISControlProtocol/Protocols/udp/ProtocolHandler.py
TISControlProtocol/Protocols/udp/UpdateCoordinator.py
TISControlProtocol/Protocols/udp/__init__.py
TISControlProtocol/Protocols/udp/PacketHandlers/AnalogFeedbackHandler.py
TISControlProtocol/Protocols/udp/PacketHandlers/AutoBinaryFeedbackHandler.py
TISControlProtocol/Protocols/udp/PacketHandlers/BinaryFeedbackHandler.py
TISControlProtocol/Protocols/udp/PacketHandlers/ClimateBinaryFeedbackHandler.py
TISControlProtocol/Protocols/udp/PacketHandlers/ClimateControlFeedbackHandler.py
TISControlProtocol/Protocols/udp/PacketHandlers/ControlResponseHandler.py
TISControlProtocol/Protocols/udp/PacketHandlers/DiscoveryFeedbackHandler.py
TISControlProtocol/Protocols/udp/PacketHandlers/EnergyFeedbackHandler.py
TISControlProtocol/Protocols/udp/PacketHandlers/FloorBinaryFeedbackHandler.py
TISControlProtocol/Protocols/udp/PacketHandlers/HealthFeedbackHandler.py
TISControlProtocol/Protocols/udp/PacketHandlers/LunaTempFeedbackHandler.py
TISControlProtocol/Protocols/udp/PacketHandlers/RealTimeFeedbackHandler.py
TISControlProtocol/Protocols/udp/PacketHandlers/SearchResponseHandler.py
TISControlProtocol/Protocols/udp/PacketHandlers/SecurityFeedbackHandler.py
TISControlProtocol/Protocols/udp/PacketHandlers/UpdateResponseHandler.py
TISControlProtocol/Protocols/udp/PacketHandlers/UpdateSecurityHandler.py
tiscontrolprotocol-1.0.47.dist-info/METADATA
tiscontrolprotocol-1.0.47.dist-info/WHEEL
tiscontrolprotocol-1.0.47.dist-info/licenses/LICENSE
tiscontrolprotocol-1.0.47.dist-info/RECORD
