Metadata-Version: 2.4
Name: TISControlProtocol
Version: 1.0.47
Summary: A library for TIS Control Protocol
Project-URL: Homepage, https://github.com/TISControlHass
Project-URL: Issues, https://github.com/TISControlHass/issues
Author-email: Ibrahim Mohamed <ibrali2001.ia@gmail.com>
License-File: LICENSE
Classifier: License :: OSI Approved :: MIT License
Classifier: Operating System :: POSIX :: Linux
Classifier: Programming Language :: Python :: 3
Requires-Python: >=3.11
